pyvmaf-1.0.0a1.dist-info/zip-safe
pyvmaf-1.0.0a1.dist-info/top_level.txt
pyvmaf-1.0.0a1.dist-info/WHEEL
pyvmaf-1.0.0a1.dist-info/METADATA
pyvmaf-1.0.0a1.dist-info/RECORD
pyvmaf-1.0.0a1.dist-info/LICENSE
pyvmaf/_vmaf.cpython-39-x86_64-linux-gnu.so
pyvmaf/core.py
pyvmaf/__init__.py
pyvmaf.libs/libvmaf-81184204.so.1.1.3
